quran_cli/__init__.py
quran_cli/__main__.py
quran_cli/assets/data/chapters.json
quran_cli/assets/data/chapters.sql
quran_cli/assets/data/comp.sql
quran_cli/assets/data/initial.sql
quran_cli/assets/data/interpretations.sql
quran_cli/assets/data/metadata.json
quran_cli/assets/data/translations.sql
quran_cli/assets/data/transliterations.sql
quran_cli/assets/schemas/comp.sql
quran_cli/assets/schemas/initial.sql
quran_cli/assets/schemas/normalized.sql
quran_cli/assets/schemas/views.sql
quran_cli/commands/__init__.py
quran_cli/commands/clear.py
quran_cli/commands/explore.py
quran_cli/commands/export.py
quran_cli/commands/init.py
quran_cli/commands/interpret.py
quran_cli/commands/normalize.py
quran_cli/main.py
quran_cli/utils.py
quran_cli-0.2.1.dist-info/entry_points.txt
quran_cli-0.2.1.dist-info/LICENSE
quran_cli-0.2.1.dist-info/METADATA
quran_cli-0.2.1.dist-info/WHEEL
quran_cli-0.2.1.dist-info/RECORD
