Metadata-Version: 2.3
Name: quran-cli
Version: 0.2.1
Summary: Quran CLI, A tool to generate the most sophisticated Quran data.
License: MIT
Author: Yousuf Abu Shanab
Author-email: josephyousef249@gmail.com
Requires-Python: >=3.10
Classifier: License :: OSI Approved :: MIT License
Classifier: Programming Language :: Python :: 3
Classifier: Programming Language :: Python :: 3.10
Classifier: Programming Language :: Python :: 3.11
Classifier: Programming Language :: Python :: 3.12
Classifier: Programming Language :: Python :: 3.13
Requires-Dist: typer (>=0.12.5)
Project-URL: Documentation, https://github.com/youzarsiph/quran-cli
Project-URL: Homepage, https://github.com/youzarsiph/quran-cli
Project-URL: Repository, https://github.com/youzarsiph/quran-cli
